tj_hyd_nam/__init__.py
tj_hyd_nam/nam_exception.py
tj_hyd_nam/tj_hyd_nam.py
tj_hyd_nam-1.1.0.dist-info/LICENSE
tj_hyd_nam-1.1.0.dist-info/METADATA
tj_hyd_nam-1.1.0.dist-info/WHEEL
tj_hyd_nam-1.1.0.dist-info/RECORD
